voice_code2.cpython-311-darwin.so
voice_code_resource2/model-en/am/final.mdl
voice_code_resource2/model-en/conf/222mfcc.conf
voice_code_resource2/model-en/conf/222model.conf
voice_code_resource2/model-en/conf/mfcc.conf
voice_code_resource2/model-en/conf/model.conf
voice_code_resource2/model-en/graph/Gr.fst
voice_code_resource2/model-en/graph/HCLr.fst
voice_code_resource2/model-en/graph/disambig_tid.int
voice_code_resource2/model-en/graph/phones/word_boundary.int
voice_code_resource2/model-en/ivector/final.dubm
voice_code_resource2/model-en/ivector/final.ie
voice_code_resource2/model-en/ivector/final.mat
voice_code_resource2/model-en/ivector/global_cmvn.stats
voice_code_resource2/model-en/ivector/online_cmvn.conf
voice_code_resource2/model-en/ivector/splice.conf
voice_code_resource2/model-en/lm/isymbols.txt
voice_code_resource2/model-en/lm/osymbols.txt
voice_code_resource2/model-en/lm/vocab.fst.txt
voice_code_resource2/model-en/lm/vocab.txt
voice_code_resource2/model-en/未命名文件夹/HCLr.fst
voice_code_resource2/model-en/未命名文件夹/HCLr.txt
voice_code2-0.0.2.dist-info/METADATA
voice_code2-0.0.2.dist-info/WHEEL
voice_code2-0.0.2.dist-info/entry_points.txt
voice_code2-0.0.2.dist-info/top_level.txt
voice_code2-0.0.2.dist-info/RECORD
