Metadata-Version: 2.1
Name: voice-code2
Version: 0.0.2
Summary: voice_code2 project
